cricri/__init__.py
cricri/__version__.py
cricri/algo.py
cricri/condition.py
cricri/cricri.py
cricri/inet/__init__.py
cricri/inet/http_client.py
cricri/inet/server.py
cricri/inet/tcp_client.py
cricri-1.4.dist-info/DESCRIPTION.rst
cricri-1.4.dist-info/METADATA
cricri-1.4.dist-info/RECORD
cricri-1.4.dist-info/WHEEL
cricri-1.4.dist-info/metadata.json
cricri-1.4.dist-info/top_level.txt
