Metadata-Version: 2.0
Name: cricri
Version: 1.4
Summary: Scenario test generator
Home-page: https://github.com/maillol/cricri
Author: Vincent Maillol
Author-email: vincent.maillol@gmail.com
License: GPLv3
Keywords: scenario test generator unittest case
Platform: UNKNOWN
Classifier: Development Status :: 5 - Production/Stable
Classifier: Intended Audience :: Developers
Classifier: Programming Language :: Python :: 3.4
Classifier: Programming Language :: Python :: 3.5
Classifier: Programming Language :: Python :: 3.6
Classifier: Topic :: Software Development :: Testing
Classifier: License :: OSI Approved :: GNU General Public License v3 (GPLv3)
Requires-Python: >=3.4
Requires-Dist: voluptuous
